arlas_permissions_api_python/__init__.py
arlas_permissions_api_python/api_client.py
arlas_permissions_api_python/configuration.py
arlas_permissions_api_python/rest.py
arlas_permissions_api_python/apis/__init__.py
arlas_permissions_api_python/apis/authorize_api.py
arlas_permissions_api_python/models/__init__.py
arlas_permissions_api_python/models/error.py
arlas_permissions_api_python/models/resource.py
test/__init__.py
test/test_authorize_api.py
test/test_error.py
test/test_resource.py
arlas_permissions_api-24.1.0.dist-info/METADATA
arlas_permissions_api-24.1.0.dist-info/WHEEL
arlas_permissions_api-24.1.0.dist-info/top_level.txt
arlas_permissions_api-24.1.0.dist-info/RECORD
