Metadata-Version: 2.1
Name: arlas-permissions-api
Version: 24.1.0
Summary: ARLAS permissions API
Home-page: https://github.com/gisaia/ARLAS-permissions
Author: Gisaïa
Author-email: contact@gisaia.com
License: UNKNOWN
Keywords: Arlas,ARLAS permissions API
Platform: UNKNOWN
Requires-Dist: urllib3 (>=1.15)
Requires-Dist: six (>=1.10)
Requires-Dist: certifi
Requires-Dist: python-dateutil
